gate/__init__.py
gate/gate.py
gate-0.0.4.dist-info/DESCRIPTION.rst
gate-0.0.4.dist-info/METADATA
gate-0.0.4.dist-info/RECORD
gate-0.0.4.dist-info/WHEEL
gate-0.0.4.dist-info/metadata.json
gate-0.0.4.dist-info/top_level.txt
