Metadata-Version: 2.0
Name: gate
Version: 0.0.4
Summary: GateFactory is the stochastic universal logic gate generator for building up a boolean expression to approximate the function
Home-page: https://github.com/mertyildiran/GateFactory
Author: Mehmet Mert Yildiran
Author-email: mert.yildiran@bil.omu.edu.tr
License: MIT
Keywords: machine learning artificial intelligence function approximation
Platform: UNKNOWN
Classifier: Development Status :: 3 - Alpha
Classifier: Intended Audience :: Developers
Classifier: Topic :: Scientific/Engineering :: Artificial Intelligence
Classifier: License :: OSI Approved :: MIT License
Classifier: Programming Language :: Python :: 2.7
